serial_uploader/__init__.py
serial_uploader-0.1.1.dist-info/LICENSE
serial_uploader-0.1.1.dist-info/METADATA
serial_uploader-0.1.1.dist-info/WHEEL
serial_uploader-0.1.1.dist-info/entry_points.txt
serial_uploader-0.1.1.dist-info/top_level.txt
serial_uploader-0.1.1.dist-info/RECORD
