Metadata-Version: 2.1
Name: serial-uploader
Version: 0.1.1
Summary: Simple serial console switch configuration uploader.
Home-page: UNKNOWN
Author: David Caro
Author-email: david@dcaro.es
Maintainer: David Caro
Maintainer-email: david@dcaro.es
License: UNKNOWN
Platform: UNKNOWN
Classifier: Programming Language :: Python
Classifier: Programming Language :: Python :: 3.7
Requires-Python: >=3.7
Requires-Dist: pyserial
Requires-Dist: click
